<?xml version="1.0" ?><annotation>
  <filename>helmet_11476.jpg</filename>
  <size>
    <width>1920</width>
    <height>1080</height>
    <depth>3</depth>
  </size>
  <object>
    <name>hat</name>
    <bndbox>
      <xmin>719</xmin>
      <ymin>268</ymin>
      <xmax>778</xmax>
      <ymax>337</ymax>
    </bndbox>
  </object>
  <object>
    <name>person</name>
    <bndbox>
      <xmin>662</xmin>
      <ymin>268</ymin>
      <xmax>830</xmax>
      <ymax>503</ymax>
    </bndbox>
  </object>
</annotation>